apisdk/__init__.py
apisdk/connection/Connection.py
apisdk/connection/Headers.py
apisdk/connection/HttpConnection.py
apisdk/connection/JwtUrlConnection.py
apisdk/connection/__init__.py
apisdk/controller/ApiController.py
apisdk/controller/__init__.py
apisdk/masking/Masking.py
apisdk/masking/__init__.py
apisdk/model/AggregatorInformation.py
apisdk/model/AmountDetails.py
apisdk/model/BillTo.py
apisdk/model/Card.py
apisdk/model/ClientReferenceInformation.py
apisdk/model/OrderInformation.py
apisdk/model/PaymentInformation.py
apisdk/model/Payments.py
apisdk/model/ProcessingInformation.py
apisdk/model/SubMerchant.py
apisdk/model/__init__.py
apisdk/service/PaymentRequestService.py
apisdk/service/__init__.py
apisdk/test/__init__.py
apisdk/test/test_ApiController.py
authenticationsdk/__init__.py
authenticationsdk/core/Authorization.py
authenticationsdk/core/ExceptionHandling.py
authenticationsdk/core/MerchantConfigaration.py
authenticationsdk/core/MockData.py
authenticationsdk/core/TokenGeneration.py
authenticationsdk/core/__init__.py
authenticationsdk/http/GetSignatureParameter.py
authenticationsdk/http/HTTPSignatureToken.py
authenticationsdk/http/__init__.py
authenticationsdk/jwt/Token.py
authenticationsdk/jwt/__init__.py
authenticationsdk/logger/Log.py
authenticationsdk/logger/__init__.py
authenticationsdk/payloaddigest/PayLoadDigest.py
authenticationsdk/payloaddigest/__init__.py
authenticationsdk/test/__init__.py
authenticationsdk/test/test_Authorization.py
authenticationsdk/util/Cache.py
authenticationsdk/util/ExceptionAuth.py
authenticationsdk/util/GlobalLabelParameters.py
authenticationsdk/util/PropertiesUtil.py
authenticationsdk/util/Utility.py
authenticationsdk/util/__init__.py
cybersource_authentication_sdk_python/__init__.py
cybersource_authentication_sdk_python/Resources/__init__.py
cybersource_authentication_sdk_python/data/Configaration.py
cybersource_authentication_sdk_python/data/RequestData.py
cybs-1.0.0.dist-info/DESCRIPTION.rst
cybs-1.0.0.dist-info/METADATA
cybs-1.0.0.dist-info/RECORD
cybs-1.0.0.dist-info/WHEEL
cybs-1.0.0.dist-info/metadata.json
cybs-1.0.0.dist-info/top_level.txt
